pylodica/__init__.py
pylodica/__main__.py
pylodica/core.py
pylodica-0.0.2.dist-info/LICENSE
pylodica-0.0.2.dist-info/METADATA
pylodica-0.0.2.dist-info/WHEEL
pylodica-0.0.2.dist-info/top_level.txt
pylodica-0.0.2.dist-info/RECORD
